clean_jetbrains_old/__init__.py
clean_jetbrains_old-0.1.15.dist-info/WHEEL
clean_jetbrains_old-0.1.15.dist-info/entry_points.txt
clean_jetbrains_old-0.1.15.dist-info/METADATA
clean_jetbrains_old-0.1.15.dist-info/RECORD
