Metadata-Version: 2.4
Name: clean-jetbrains-old
Version: 0.1.15
Summary: Add your description here
Author: GideonBear
License-Expression: GPL-3.0-only
Classifier: License :: OSI Approved :: GNU General Public License v3 (GPLv3)
Classifier: Programming Language :: Python :: 3 :: Only
Classifier: Programming Language :: Python :: 3.13
Requires-Dist: packaging>=24
Requires-Python: >=3.13
Project-URL: bugs, https://github.com/GideonBear/clean-jetbrains-old/issues
Project-URL: homepage, https://github.com/GideonBear/clean-jetbrains-old
